python_test_package/__init__.py
python_test_package/__main__.py
python_test_package-0.1.post1.dist-info/DESCRIPTION.rst
python_test_package-0.1.post1.dist-info/METADATA
python_test_package-0.1.post1.dist-info/RECORD
python_test_package-0.1.post1.dist-info/WHEEL
python_test_package-0.1.post1.dist-info/metadata.json
python_test_package-0.1.post1.dist-info/top_level.txt
