Metadata-Version: 2.0
Name: python-test-package
Version: 0.1.post1
Summary: Add description here.
Home-page: https://github.com/wheeler-microfluidics/python-test-package
Author: Anonymous
Author-email: you@mail.com
License: GPL
Platform: UNKNOWN
